space_escape/__init__.py
space_escape/main.py
space_escape/assets/.DS_Store
space_escape/assets/fonts/BalooChettan2-Bold.ttf
space_escape/assets/fonts/BalooChettan2-ExtraBold.ttf
space_escape/assets/fonts/BalooChettan2-Medium.ttf
space_escape/assets/fonts/BalooChettan2-Regular.ttf
space_escape/assets/fonts/BalooChettan2-SemiBold.ttf
space_escape/assets/images/blue.png
space_escape/assets/images/meteorBrown_small1.png
space_escape/assets/images/meteorBrown_small2.png
space_escape/assets/images/meteorBrown_tiny1.png
space_escape/assets/images/meteorBrown_tiny2.png
space_escape/assets/images/playerLife1_blue.png
space_escape/assets/images/playerShip1_blue.png
space_escape/assets/images/purple.png
space_escape/assets/images/meteors/meteorBrown_big1.png
space_escape/assets/images/meteors/meteorBrown_big2.png
space_escape/assets/images/meteors/meteorBrown_big3.png
space_escape/assets/images/meteors/meteorBrown_big4.png
space_escape/assets/images/meteors/meteorBrown_med1.png
space_escape/assets/images/meteors/meteorBrown_med3.png
space_escape/assets/images/meteors/meteorBrown_small1.png
space_escape/assets/images/meteors/meteorBrown_small2.png
space_escape/assets/images/meteors/meteorBrown_tiny1.png
space_escape/assets/images/meteors/meteorBrown_tiny2.png
space_escape/assets/images/meteors/meteorGrey_big1.png
space_escape/assets/images/meteors/meteorGrey_big2.png
space_escape/assets/images/meteors/meteorGrey_big3.png
space_escape/assets/images/meteors/meteorGrey_big4.png
space_escape/assets/images/meteors/meteorGrey_med1.png
space_escape/assets/images/meteors/meteorGrey_med2.png
space_escape/assets/images/meteors/meteorGrey_small1.png
space_escape/assets/images/meteors/meteorGrey_small2.png
space_escape/assets/images/meteors/meteorGrey_tiny1.png
space_escape/assets/images/meteors/meteorGrey_tiny2.png
space_escape/assets/sounds/bensound-game.ogg
space_escape/assets/sounds/bensound-menu.ogg
space_escape/assets/sounds/sfx_lose.ogg
space_escape/assets/sounds/sfx_zap.ogg
space_escape_raksoiv-0.4.0.dist-info/LICENSE
space_escape_raksoiv-0.4.0.dist-info/METADATA
space_escape_raksoiv-0.4.0.dist-info/WHEEL
space_escape_raksoiv-0.4.0.dist-info/entry_points.txt
space_escape_raksoiv-0.4.0.dist-info/top_level.txt
space_escape_raksoiv-0.4.0.dist-info/RECORD
