Metadata-Version: 2.1
Name: space-escape-raksoiv
Version: 0.4.0
Summary: Space Escape is a 2D simple endless horizontal scrolling of a space ship avoiding asteroids made with PyGame
Home-page: https://github.com/Raksoiv/space-escape
Author: Oscar Rencoret
Author-email: o.rencoret@gmail.com
License: UNKNOWN
Platform: UNKNOWN
Classifier: Development Status :: 3 - Alpha
Classifier: Environment :: Console
Classifier: License :: OSI Approved :: GNU General Public License (GPL)
Classifier: Operating System :: OS Independent
Classifier: Programming Language :: Python :: 3
Classifier: Topic :: Games/Entertainment :: Arcade
Classifier: Topic :: Software Development :: Libraries :: pygame
Requires-Python: >=3.7
Requires-Dist: pygame
